bin
m3s_scraper
