Metadata-Version: 1.0
Name: m3s-scraper
Version: 0.3.2
Summary: A tool for exporting M3S data
Home-page: https://github.com/themotionmachine/m3s_scrapert
Author: RTW
Author-email: ryan_t_w@utexas.edu
License: MIT
Platform: UNKNOWN
